rss_reader/__init__.py
rss_reader/__main__.py
rss_reader/rss_reader.py
rss_reader/argument_parser/__init__.py
rss_reader/argument_parser/arg_parser.py
rss_reader/converters/__init__.py
rss_reader/converters/displayer.py
rss_reader/converters/file_converters.py
rss_reader/tests/__init__.py
rss_reader/tests/unit/__init__.py
rss_reader/tests/unit/test_argparse.py
rss_reader/tests/unit/test_caching.py
rss_reader/tests/unit/test_log.py
rss_reader/tests/unit/test_rss_reader.py
rss_reader/utils/__init__.py
rss_reader/utils/caching.py
rss_reader/utils/custom_exceptions.py
rss_reader/utils/log.py
daily_rss_news-5.0.4.dist-info/LICENSE
daily_rss_news-5.0.4.dist-info/METADATA
daily_rss_news-5.0.4.dist-info/WHEEL
daily_rss_news-5.0.4.dist-info/entry_points.txt
daily_rss_news-5.0.4.dist-info/top_level.txt
daily_rss_news-5.0.4.dist-info/RECORD
