Metadata-Version: 2.1
Name: daily-rss-news
Version: 5.0.4
Summary: UNKNOWN
Home-page: https://gitlab.com/Ilhom_Xusanov/RSS-parser
Author: Ilhom Xusanov
Author-email: xusanov2390@gmail.com
License: UNKNOWN
Platform: UNKNOWN
Classifier: Programming Language :: Python :: 3
Classifier: License :: OSI Approved :: MIT License
Classifier: Operating System :: OS Independent
Requires-Python: >=3.6
License-File: LICENSE
Requires-Dist: requests
Requires-Dist: lxml
Requires-Dist: beautifulsoup4
Requires-Dist: pytest
Requires-Dist: pytest-cov
Requires-Dist: python-dateutil
Requires-Dist: fpdf2
Requires-Dist: PyPDF2
Requires-Dist: colorama
